abx_plugin_readwise.py
abx_plugin_readwise-2024.10.28.dist-info/METADATA
abx_plugin_readwise-2024.10.28.dist-info/WHEEL
abx_plugin_readwise-2024.10.28.dist-info/entry_points.txt
abx_plugin_readwise-2024.10.28.dist-info/RECORD
